Metadata-Version: 2.1
Name: magnets
Version: 0.1.5
Summary: A Python package to aggregate and reduce water distribution network models
Home-page: https://github.com/meghnathomas/magnets
Author: Meghna Sarah Thomas
Author-email: meghnathomas@utexas.edu
License: MIT license
Keywords: magnets
Platform: UNKNOWN
Classifier: Development Status :: 2 - Pre-Alpha
Classifier: Intended Audience :: Developers
Classifier: License :: OSI Approved :: MIT License
Classifier: Natural Language :: English
Classifier: Programming Language :: Python :: 3
Classifier: Programming Language :: Python :: 3.6
Classifier: Programming Language :: Python :: 3.7
Classifier: Programming Language :: Python :: 3.8
Requires-Python: >=3.6
